<?xml version="1.0" encoding="UTF-8"?><record_update sys_domain="global" table="sysevent_email_action">
    <sysevent_email_action action="INSERT_OR_UPDATE">
        <action_insert>true</action_insert>
        <action_update>true</action_update>
        <active>true</active>
        <advanced_condition/>
        <affected_field_on_event/>
        <category display_value="SDLC" name="SDLC">be9d02137f232200ee2e108c3ffa9152</category>
        <collection>idea</collection>
        <condition table="idea">assignment_groupVALCHANGES^assignment_groupISNOTEMPTY^assigned_toISEMPTY^active=true^EQ<item endquery="false" field="assignment_group" goto="false" newquery="false" operator="VALCHANGES" or="false" value=""/>
            <item endquery="false" field="assignment_group" goto="false" newquery="false" operator="ISNOTEMPTY" or="false" value=""/>
            <item endquery="false" field="assigned_to" goto="false" newquery="false" operator="ISEMPTY" or="false" value=""/>
            <item endquery="false" field="active" goto="false" newquery="false" operator="=" or="false" value="true"/>
            <item endquery="true" field="" goto="false" newquery="false" operator="=" or="false" value=""/>
        </condition>
        <content_type>text/html</content_type>
        <default_interval/>
        <description/>
        <digest_from/>
        <digest_html/>
        <digest_reply_to/>
        <digest_separator_html><![CDATA[<p>&nbsp;</p>
<hr />
<p>&nbsp;</p>]]></digest_separator_html>
        <digest_separator_text><![CDATA[\n--------------------------------------------------------------------------------\n]]></digest_separator_text>
        <digest_subject/>
        <digest_template/>
        <digest_text/>
        <digestable>false</digestable>
        <event_name>x_44813_usasoc_cst.idea.new</event_name>
        <event_parm_1>false</event_parm_1>
        <event_parm_2>false</event_parm_2>
        <exclude_delegates>false</exclude_delegates>
        <force_delivery>false</force_delivery>
        <from/>
        <generation_type>engine</generation_type>
        <importance/>
        <include_attachments>false</include_attachments>
        <item>event.parm1</item>
        <item_table/>
        <mandatory>false</mandatory>
        <message/>
        <message_html><![CDATA[<p>Idea ${URI_REF},&nbsp;submitted by: ${opened_by}, has been assigned to one of your groups.</p>
<p>Title: ${short_description}</p>
<p>Description(business_case): ${business_case}</p>]]></message_html>
        <message_list/>
        <message_text/>
        <name>Idea Assigned to Group</name>
        <omit_watermark>false</omit_watermark>
        <order>100</order>
        <push_message_only>false</push_message_only>
        <recipient_fields>assignment_group</recipient_fields>
        <recipient_groups/>
        <recipient_users/>
        <reply_to/>
        <send_self>true</send_self>
        <sms_alternate/>
        <style/>
        <subject>Idea ${number} has been assigned to group ${assignment_group}</subject>
        <subscribable>false</subscribable>
        <sys_class_name>sysevent_email_action</sys_class_name>
        <sys_created_by>erwinel_da</sys_created_by>
        <sys_created_on>2020-02-03 21:12:31</sys_created_on>
        <sys_domain>global</sys_domain>
        <sys_domain_path>/</sys_domain_path>
        <sys_id>7f00823407f20010683af0269c1ed053</sys_id>
        <sys_mod_count>5</sys_mod_count>
        <sys_name>Idea Assigned to Group</sys_name>
        <sys_overrides/>
        <sys_package display_value="USASOC Customizations (erwinel)" source="x_44813_usasoc_cst">2872713307620010683af0269c1ed0fc</sys_package>
        <sys_policy/>
        <sys_scope display_value="USASOC Customizations (erwinel)">2872713307620010683af0269c1ed0fc</sys_scope>
        <sys_update_name>sysevent_email_action_7f00823407f20010683af0269c1ed053</sys_update_name>
        <sys_updated_by>erwinel_da</sys_updated_by>
        <sys_updated_on>2020-02-04 19:26:52</sys_updated_on>
        <sys_version>2</sys_version>
        <template display_value="Unsubscribe and Preferences Helvetica">d465111f3b4b2200c869c2c703efc47c</template>
        <type>email</type>
        <weight>0</weight>
    </sysevent_email_action>
</record_update>
